[{"termname":"Winter 2025-2026","districtname":"Alpha","district_stateid":"","schoolname":"Alpha Plano","school_stateid":"","studentid":"042-4214","student_stateid":"","subject":"Math","course":"Math K-12","growthmeasureyn":"","normsreferencedata":"2025","wiselectedayfall":"1","wiselectedaywinter":"20","wiselectedayspring":"","wipreviousayfall":"","wipreviousaywinter":"","wipreviousayspring":"","testtype":"Survey With Goals","testname":"Growth: Math K-2 CCSS 2010 1.1","testid":"","teststartdate":"2026-02-03","teststarttime":"09:02:21","testdurationminutes":"17","testritscore":"156","teststandarderror":"3.21","testpercentile":"","achievementquintile":"","percentcorrect":"52","rapidguessingpercentage":"0.0","falltofallprojectedgrowth":"","falltofallobservedgrowth":"","falltofallobservedgrowthse":"","falltofallmetprojectedgrowth":"","falltofallconditionalgrowthindex":"","falltofallconditionalgrowthpercentile":"","falltofallgrowthquintile":"","falltowinterprojectedgrowth":"","falltowinterobservedgrowth":"16.0","falltowinterobservedgrowthse":"4.52","falltowintermetprojectedgrowth":"","falltowinterconditionalgrowthindex":"","falltowinterconditionalgrowthpercentile":"","falltowintergrowthquintile":"","falltospringprojectedgrowth":"","falltospringobservedgrowth":"","falltospringobservedgrowthse":"","falltospringmetprojectedgrowth":"","falltospringconditionalgrowthindex":"","falltospringconditionalgrowthpercentile":"","falltospringgrowthquintile":"","wintertowinterprojectedgrowth":"","wintertowinterobservedgrowth":"","wintertowinterobservedgrowthse":"","wintertowintermetprojectedgrowth":"","wintertowinterconditionalgrowthindex":"","wintertowinterconditionalgrowthpercentile":"","wintertowintergrowthquintile":"","wintertospringprojectedgrowth":"","wintertospringobservedgrowth":"","wintertospringobservedgrowthse":"","wintertospringmetprojectedgrowth":"","wintertospringconditionalgrowthindex":"","wintertospringconditionalgrowthpercentile":"","wintertospringgrowthquintile":"","springtospringprojectedgrowth":"","springtospringobservedgrowth":"","springtospringobservedgrowthse":"","springtospringmetprojectedgrowth":"","springtospringconditionalgrowthindex":"","springtospringconditionalgrowthpercentile":"","springtospringgrowthquintile":"","lexilescore":"","lexilemin":"","lexilemax":"","quantilescore":"","quantilemin":"","quantilemax":"","goal1name":"Operations and Algebraic Thinking","goal1ritscore":"160.0","goal1stderr":"6.3","goal1range":"154-166","goal1adjective":"","goal2name":"Number and Operations","goal2ritscore":"147.0","goal2stderr":"6.2","goal2range":"141-153","goal2adjective":"","goal3name":"Measurement and Data","goal3ritscore":"158.0","goal3stderr":"6.2","goal3range":"152-164","goal3adjective":"","goal4name":"Geometry","goal4ritscore":"165","goal4stderr":"8.9","goal4range":"156-174","goal4adjective":"","goal5name":"","goal5ritscore":"","goal5stderr":"","goal5range":"","goal5adjective":"","goal6name":"","goal6ritscore":"","goal6stderr":"","goal6range":"","goal6adjective":"","goal7name":"","goal7ritscore":"","goal7stderr":"","goal7range":"","goal7adjective":"","goal8name":"","goal8ritscore":"","goal8stderr":"","goal8range":"","goal8adjective":"","typicalfalltofallgrowth":"","typicalfalltowintergrowth":"","typicalfalltospringgrowth":"","typicalwintertowintergrowth":"","typicalwintertospringgrowth":"","typicalspringtospringgrowth":"","projectedproficiencystudy1":"","projectedproficiencylevel1":"","projectedproficiencystudy2":"","projectedproficiencylevel2":"","projectedproficiencystudy3":"","projectedproficiencylevel3":"","projectedproficiencystudy4":"","projectedproficiencylevel4":"","projectedproficiencystudy5":"","projectedproficiencylevel5":"","projectedproficiencystudy6":"","projectedproficiencylevel6":"","projectedproficiencystudy7":"","projectedproficiencylevel7":"","projectedproficiencystudy8":"","projectedproficiencylevel8":"","projectedproficiencystudy9":"","projectedproficiencylevel9":"","projectedproficiencystudy10":"","projectedproficiencylevel10":"","classname":"-1","teachername":"Beckley, Kristen","teacherid":"AssessAlpha","teacher_stateid":"","studentlastname":"Bryan","studentfirstname":"Liam","studentmi":"","studentdateofbirth":"2020-11-01","studentethnicgroup":"Not Specified or Other","nweastandard_ethnicgroup":"Not Specified or Other","studentgender":"M","grade":"PK","nweastandard_grade":"PK","learningrate":"","termprojectedgrowth":"","termobservedgrowth":"","teststartdatelatestinterm":"","minstandarderror":""},{"termname":"Winter 2025-2026","districtname":"Alpha","district_stateid":"","schoolname":"Alpha Plano","school_stateid":"","studentid":"042-4215","student_stateid":"","subject":"Math","course":"Math K-12","growthmeasureyn":"","normsreferencedata":"2025","wiselectedayfall":"1","wiselectedaywinter":"20","wiselectedayspring":"","wipreviousayfall":"","wipreviousaywinter":"","wipreviousayspring":"","testtype":"Survey With Goals","testname":"Growth: Math 2-5 CCSS 2010 1.1","testid":"","teststartdate":"2026-02-03","teststarttime":"09:14:52","testdurationminutes":"38","testritscore":"183","teststandarderror":"3.25","testpercentile":"28","achievementquintile":"LoAvg","percentcorrect":"50","rapidguessingpercentage":"0.0","falltofallprojectedgrowth":"","falltofallobservedgrowth":"","falltofallobservedgrowthse":"","falltofallmetprojectedgrowth":"","falltofallconditionalgrowthindex":"","falltofallconditionalgrowthpercentile":"","falltofallgrowthquintile":"","falltowinterprojectedgrowth":"11.0","falltowinterobservedgrowth":"6.0","falltowinterobservedgrowthse":"4.61","falltowintermetprojectedgrowth":"No","falltowinterconditionalgrowthindex":"-0.61","falltowinterconditionalgrowthpercentile":"27.0","falltowintergrowthquintile":"LoAvg","falltospringprojectedgrowth":"","falltospringobservedgrowth":"","falltospringobservedgrowthse":"","falltospringmetprojectedgrowth":"","falltospringconditionalgrowthindex":"","falltospringconditionalgrowthpercentile":"","falltospringgrowthquintile":"","wintertowinterprojectedgrowth":"","wintertowinterobservedgrowth":"","wintertowinterobservedgrowthse":"","wintertowintermetprojectedgrowth":"","wintertowinterconditionalgrowthindex":"","wintertowinterconditionalgrowthpercentile":"","wintertowintergrowthquintile":"","wintertospringprojectedgrowth":"","wintertospringobservedgrowth":"","wintertospringobservedgrowthse":"","wintertospringmetprojectedgrowth":"","wintertospringconditionalgrowthindex":"","wintertospringconditionalgrowthpercentile":"","wintertospringgrowthquintile":"","springtospringprojectedgrowth":"","springtospringobservedgrowth":"","springtospringobservedgrowthse":"","springtospringmetprojectedgrowth":"","springtospringconditionalgrowthindex":"","springtospringconditionalgrowthpercentile":"","springtospringgrowthquintile":"","lexilescore":"","lexilemin":"","lexilemax":"","quantilescore":"175Q","quantilemin":"125Q","quantilemax":"225Q","goal1name":"Operations and Algebraic Thinking","goal1ritscore":"180.0","goal1stderr":"6.7","goal1range":"173-187","goal1adjective":"LoAvg","goal2name":"Number and Operations","goal2ritscore":"182.0","goal2stderr":"5.7","goal2range":"176-188","goal2adjective":"LoAvg","goal3name":"Measurement and Data","goal3ritscore":"184.0","goal3stderr":"6.3","goal3range":"178-190","goal3adjective":"LoAvg","goal4name":"Geometry","goal4ritscore":"189","goal4stderr":"8.7","goal4range":"180-198","goal4adjective":"Avg","goal5name":"","goal5ritscore":"","goal5stderr":"","goal5range":"","goal5adjective":"","goal6name":"","goal6ritscore":"","goal6stderr":"","goal6range":"","goal6adjective":"","goal7name":"","goal7ritscore":"","goal7stderr":"","goal7range":"","goal7adjective":"","goal8name":"","goal8ritscore":"","goal8stderr":"","goal8range":"","goal8adjective":"","typicalfalltofallgrowth":"","typicalfalltowintergrowth":"","typicalfalltospringgrowth":"","typicalwintertowintergrowth":"13.0","typicalwintertospringgrowth":"7.0","typicalspringtospringgrowth":"","projectedproficiencystudy1":"","projectedproficiencylevel1":"","projectedproficiencystudy2":"","projectedproficiencylevel2":"","projectedproficiencystudy3":"STAAR","projectedproficiencylevel3":"Did Not Meet","projectedproficiencystudy4":"","projectedproficiencylevel4":"","projectedproficiencystudy5":"","projectedproficiencylevel5":"","projectedproficiencystudy6":"","projectedproficiencylevel6":"","projectedproficiencystudy7":"","projectedproficiencylevel7":"","projectedproficiencystudy8":"","projectedproficiencylevel8":"","projectedproficiencystudy9":"","projectedproficiencylevel9":"","projectedproficiencystudy10":"","projectedproficiencylevel10":"","classname":"1","teachername":"Beckley, Kristen","teacherid":"AssessAlpha","teacher_stateid":"","studentlastname":"Stone","studentfirstname":"Sofia","studentmi":"","studentdateofbirth":"2016-07-31","studentethnicgroup":"Not Specified or Other","nweastandard_ethnicgroup":"Not Specified or Other","studentgender":"X","grade":"3","nweastandard_grade":"3","learningrate":"","termprojectedgrowth":"","termobservedgrowth":"","teststartdatelatestinterm":"","minstandarderror":""},{"termname":"Winter 2025-2026","districtname":"Alpha","district_stateid":"","schoolname":"Alpha Plano","school_stateid":"","studentid":"042-4216","student_stateid":"","subject":"Math","course":"Math K-12","growthmeasureyn":"","normsreferencedata":"2025","wiselectedayfall":"1","wiselectedaywinter":"20","wiselectedayspring":"","wipreviousayfall":"","wipreviousaywinter":"","wipreviousayspring":"","testtype":"Survey With Goals","testname":"Growth: Math K-2 CCSS 2010 1.1","testid":"","teststartdate":"2026-02-03","teststarttime":"09:03:29","testdurationminutes":"24","testritscore":"174","teststandarderror":"3.28","testpercentile":"66","achievementquintile":"HiAvg","percentcorrect":"48","rapidguessingpercentage":"0.0","falltofallprojectedgrowth":"","falltofallobservedgrowth":"","falltofallobservedgrowthse":"","falltofallmetprojectedgrowth":"","falltofallconditionalgrowthindex":"","falltofallconditionalgrowthpercentile":"","falltofallgrowthquintile":"","falltowinterprojectedgrowth":"10.0","falltowinterobservedgrowth":"9.0","falltowinterobservedgrowthse":"4.55","falltowintermetprojectedgrowth":"No*","falltowinterconditionalgrowthindex":"-0.1","falltowinterconditionalgrowthpercentile":"46.0","falltowintergrowthquintile":"Avg","falltospringprojectedgrowth":"","falltospringobservedgrowth":"","falltospringobservedgrowthse":"","falltospringmetprojectedgrowth":"","falltospringconditionalgrowthindex":"","falltospringconditionalgrowthpercentile":"","falltospringgrowthquintile":"","wintertowinterprojectedgrowth":"","wintertowinterobservedgrowth":"","wintertowinterobservedgrowthse":"","wintertowintermetprojectedgrowth":"","wintertowinterconditionalgrowthindex":"","wintertowinterconditionalgrowthpercentile":"","wintertowintergrowthquintile":"","wintertospringprojectedgrowth":"","wintertospringobservedgrowth":"","wintertospringobservedgrowthse":"","wintertospringmetprojectedgrowth":"","wintertospringconditionalgrowthindex":"","wintertospringconditionalgrowthpercentile":"","wintertospringgrowthquintile":"","springtospringprojectedgrowth":"","springtospringobservedgrowth":"","springtospringobservedgrowthse":"","springtospringmetprojectedgrowth":"","springtospringconditionalgrowthindex":"","springtospringconditionalgrowthpercentile":"","springtospringgrowthquintile":"","lexilescore":"","lexilemin":"","lexilemax":"","quantilescore":"20Q","quantilemin":"EM30Q","quantilemax":"70Q","goal1name":"Operations and Algebraic Thinking","goal1ritscore":"174.0","goal1stderr":"6.4","goal1range":"168-180","goal1adjective":"HiAvg","goal2name":"Number and Operations","goal2ritscore":"173.0","goal2stderr":"5.8","goal2range":"167-179","goal2adjective":"HiAvg","goal3name":"Measurement and Data","goal3ritscore":"185.0","goal3stderr":"6.5","goal3range":"178-192","goal3adjective":"High","goal4name":"Geometry","goal4ritscore":"142","goal4stderr":"16.6","goal4range":"125-159","goal4adjective":"Low","goal5name":"","goal5ritscore":"","goal5stderr":"","goal5range":"","goal5adjective":"","goal6name":"","goal6ritscore":"","goal6stderr":"","goal6range":"","goal6adjective":"","goal7name":"","goal7ritscore":"","goal7stderr":"","goal7range":"","goal7adjective":"","goal8name":"","goal8ritscore":"","goal8stderr":"","goal8range":"","goal8adjective":"","typicalfalltofallgrowth":"","typicalfalltowintergrowth":"","typicalfalltospringgrowth":"","typicalwintertowintergrowth":"13.0","typicalwintertospringgrowth":"6.0","typicalspringtospringgrowth":"","projectedproficiencystudy1":"","projectedproficiencylevel1":"","projectedproficiencystudy2":"","projectedproficiencylevel2":"","projectedproficiencystudy3":"","projectedproficiencylevel3":"","projectedproficiencystudy4":"","projectedproficiencylevel4":"","projectedproficiencystudy5":"","projectedproficiencylevel5":"","projectedproficiencystudy6":"","projectedproficiencylevel6":"","projectedproficiencystudy7":"","projectedproficiencylevel7":"","projectedproficiencystudy8":"","projectedproficiencylevel8":"","projectedproficiencystudy9":"","projectedproficiencylevel9":"","projectedproficiencystudy10":"","projectedproficiencylevel10":"","classname":"0","teachername":"Beckley, Kristen","teacherid":"AssessAlpha","teacher_stateid":"","studentlastname":"Stone","studentfirstname":"Max","studentmi":"","studentdateofbirth":"2019-02-14","studentethnicgroup":"Not Specified or Other","nweastandard_ethnicgroup":"Not Specified or Other","studentgender":"M","grade":"1","nweastandard_grade":"1","learningrate":"","termprojectedgrowth":"","termobservedgrowth":"","teststartdatelatestinterm":"","minstandarderror":""},{"termname":"Winter 2025-2026","districtname":"Alpha","district_stateid":"","schoolname":"Alpha Plano","school_stateid":"","studentid":"042-7697","student_stateid":"","subject":"Math","course":"Math K-12","growthmeasureyn":"","normsreferencedata":"2025","wiselectedayfall":"","wiselectedaywinter":"20","wiselectedayspring":"","wipreviousayfall":"","wipreviousaywinter":"","wipreviousayspring":"","testtype":"Survey With Goals","testname":"Growth: Math 2-5 CCSS 2010 1.1","testid":"","teststartdate":"2026-02-03","teststarttime":"09:08:15","testdurationminutes":"23","testritscore":"206","teststandarderror":"3.27","testpercentile":"79","achievementquintile":"HiAvg","percentcorrect":"59","rapidguessingpercentage":"0.0","falltofallprojectedgrowth":"","falltofallobservedgrowth":"","falltofallobservedgrowthse":"","falltofallmetprojectedgrowth":"","falltofallconditionalgrowthindex":"","falltofallconditionalgrowthpercentile":"","falltofallgrowthquintile":"","falltowinterprojectedgrowth":"","falltowinterobservedgrowth":"","falltowinterobservedgrowthse":"","falltowintermetprojectedgrowth":"","falltowinterconditionalgrowthindex":"","falltowinterconditionalgrowthpercentile":"","falltowintergrowthquintile":"","falltospringprojectedgrowth":"","falltospringobservedgrowth":"","falltospringobservedgrowthse":"","falltospringmetprojectedgrowth":"","falltospringconditionalgrowthindex":"","falltospringconditionalgrowthpercentile":"","falltospringgrowthquintile":"","wintertowinterprojectedgrowth":"","wintertowinterobservedgrowth":"","wintertowinterobservedgrowthse":"","wintertowintermetprojectedgrowth":"","wintertowinterconditionalgrowthindex":"","wintertowinterconditionalgrowthpercentile":"","wintertowintergrowthquintile":"","wintertospringprojectedgrowth":"","wintertospringobservedgrowth":"","wintertospringobservedgrowthse":"","wintertospringmetprojectedgrowth":"","wintertospringconditionalgrowthindex":"","wintertospringconditionalgrowthpercentile":"","wintertospringgrowthquintile":"","springtospringprojectedgrowth":"","springtospringobservedgrowth":"","springtospringobservedgrowthse":"","springtospringmetprojectedgrowth":"","springtospringconditionalgrowthindex":"","springtospringconditionalgrowthpercentile":"","springtospringgrowthquintile":"","lexilescore":"","lexilemin":"","lexilemax":"","quantilescore":"575Q","quantilemin":"525Q","quantilemax":"625Q","goal1name":"Operations and Algebraic Thinking","goal1ritscore":"209.0","goal1stderr":"6.5","goal1range":"202-216","goal1adjective":"High","goal2name":"Number and Operations","goal2ritscore":"205.0","goal2stderr":"5.6","goal2range":"199-211","goal2adjective":"HiAvg","goal3name":"Measurement and Data","goal3ritscore":"208.0","goal3stderr":"6.4","goal3range":"202-214","goal3adjective":"High","goal4name":"Geometry","goal4ritscore":"198","goal4stderr":"8.8","goal4range":"189-207","goal4adjective":"HiAvg","goal5name":"","goal5ritscore":"","goal5stderr":"","goal5range":"","goal5adjective":"","goal6name":"","goal6ritscore":"","goal6stderr":"","goal6range":"","goal6adjective":"","goal7name":"","goal7ritscore":"","goal7stderr":"","goal7range":"","goal7adjective":"","goal8name":"","goal8ritscore":"","goal8stderr":"","goal8range":"","goal8adjective":"","typicalfalltofallgrowth":"","typicalfalltowintergrowth":"","typicalfalltospringgrowth":"","typicalwintertowintergrowth":"11.0","typicalwintertospringgrowth":"6.0","typicalspringtospringgrowth":"","projectedproficiencystudy1":"","projectedproficiencylevel1":"","projectedproficiencystudy2":"","projectedproficiencylevel2":"","projectedproficiencystudy3":"STAAR","projectedproficiencylevel3":"Meets","projectedproficiencystudy4":"","projectedproficiencylevel4":"","projectedproficiencystudy5":"","projectedproficiencylevel5":"","projectedproficiencystudy6":"","projectedproficiencylevel6":"","projectedproficiencystudy7":"","projectedproficiencylevel7":"","projectedproficiencystudy8":"","projectedproficiencylevel8":"","projectedproficiencystudy9":"","projectedproficiencylevel9":"","projectedproficiencystudy10":"","projectedproficiencylevel10":"","classname":"1","teachername":"Beckley, Kristen","teacherid":"AssessAlpha","teacher_stateid":"","studentlastname":"Pogue","studentfirstname":"Hayden","studentmi":"","studentdateofbirth":"2016-08-14","studentethnicgroup":"Not Specified or Other","nweastandard_ethnicgroup":"Not Specified or Other","studentgender":"M","grade":"3","nweastandard_grade":"3","learningrate":"","termprojectedgrowth":"","termobservedgrowth":"","teststartdatelatestinterm":"","minstandarderror":""},{"termname":"Winter 2025-2026","districtname":"Alpha","district_stateid":"","schoolname":"Alpha Plano","school_stateid":"","studentid":"042-7698","student_stateid":"","subject":"Math","course":"Math K-12","growthmeasureyn":"","normsreferencedata":"2025","wiselectedayfall":"","wiselectedaywinter":"20","wiselectedayspring":"","wipreviousayfall":"","wipreviousaywinter":"","wipreviousayspring":"","testtype":"Survey With Goals","testname":"Growth: Math K-2 CCSS 2010 1.1","testid":"","teststartdate":"2026-02-03","teststarttime":"09:03:13","testdurationminutes":"55","testritscore":"195","teststandarderror":"3.38","testpercentile":"97","achievementquintile":"High","percentcorrect":"60","rapidguessingpercentage":"0.0","falltofallprojectedgrowth":"","falltofallobservedgrowth":"","falltofallobservedgrowthse":"","falltofallmetprojectedgrowth":"","falltofallconditionalgrowthindex":"","falltofallconditionalgrowthpercentile":"","falltofallgrowthquintile":"","falltowinterprojectedgrowth":"","falltowinterobservedgrowth":"","falltowinterobservedgrowthse":"","falltowintermetprojectedgrowth":"","falltowinterconditionalgrowthindex":"","falltowinterconditionalgrowthpercentile":"","falltowintergrowthquintile":"","falltospringprojectedgrowth":"","falltospringobservedgrowth":"","falltospringobservedgrowthse":"","falltospringmetprojectedgrowth":"","falltospringconditionalgrowthindex":"","falltospringconditionalgrowthpercentile":"","falltospringgrowthquintile":"","wintertowinterprojectedgrowth":"","wintertowinterobservedgrowth":"","wintertowinterobservedgrowthse":"","wintertowintermetprojectedgrowth":"","wintertowinterconditionalgrowthindex":"","wintertowinterconditionalgrowthpercentile":"","wintertowintergrowthquintile":"","wintertospringprojectedgrowth":"","wintertospringobservedgrowth":"","wintertospringobservedgrowthse":"","wintertospringmetprojectedgrowth":"","wintertospringconditionalgrowthindex":"","wintertospringconditionalgrowthpercentile":"","wintertospringgrowthquintile":"","springtospringprojectedgrowth":"","springtospringobservedgrowth":"","springtospringobservedgrowthse":"","springtospringmetprojectedgrowth":"","springtospringconditionalgrowthindex":"","springtospringconditionalgrowthpercentile":"","springtospringgrowthquintile":"","lexilescore":"","lexilemin":"","lexilemax":"","quantilescore":"385Q","quantilemin":"335Q","quantilemax":"435Q","goal1name":"Operations and Algebraic Thinking","goal1ritscore":"182.0","goal1stderr":"6.9","goal1range":"175-189","goal1adjective":"High","goal2name":"Number and Operations","goal2ritscore":"209.0","goal2stderr":"8.0","goal2range":"201-217","goal2adjective":"High","goal3name":"Measurement and Data","goal3ritscore":"194.0","goal3stderr":"6.8","goal3range":"187-201","goal3adjective":"High","goal4name":"Geometry","goal4ritscore":"203","goal4stderr":"9.2","goal4range":"194-212","goal4adjective":"High","goal5name":"","goal5ritscore":"","goal5stderr":"","goal5range":"","goal5adjective":"","goal6name":"","goal6ritscore":"","goal6stderr":"","goal6range":"","goal6adjective":"","goal7name":"","goal7ritscore":"","goal7stderr":"","goal7range":"","goal7adjective":"","goal8name":"","goal8ritscore":"","goal8stderr":"","goal8range":"","goal8adjective":"","typicalfalltofallgrowth":"","typicalfalltowintergrowth":"","typicalfalltospringgrowth":"","typicalwintertowintergrowth":"12.0","typicalwintertospringgrowth":"4.0","typicalspringtospringgrowth":"","projectedproficiencystudy1":"","projectedproficiencylevel1":"","projectedproficiencystudy2":"","projectedproficiencylevel2":"","projectedproficiencystudy3":"","projectedproficiencylevel3":"","projectedproficiencystudy4":"","projectedproficiencylevel4":"","projectedproficiencystudy5":"","projectedproficiencylevel5":"","projectedproficiencystudy6":"","projectedproficiencylevel6":"","projectedproficiencystudy7":"","projectedproficiencylevel7":"","projectedproficiencystudy8":"","projectedproficiencylevel8":"","projectedproficiencystudy9":"","projectedproficiencylevel9":"","projectedproficiencystudy10":"","projectedproficiencylevel10":"","classname":"0","teachername":"Beckley, Kristen","teacherid":"AssessAlpha","teacher_stateid":"","studentlastname":"Pogue","studentfirstname":"Charlotte","studentmi":"","studentdateofbirth":"2018-07-12","studentethnicgroup":"Not Specified or Other","nweastandard_ethnicgroup":"Not Specified or Other","studentgender":"F","grade":"1","nweastandard_grade":"1","learningrate":"","termprojectedgrowth":"","termobservedgrowth":"","teststartdatelatestinterm":"","minstandarderror":""},{"termname":"Winter 2025-2026","districtname":"Alpha","district_stateid":"","schoolname":"Alpha Plano","school_stateid":"","studentid":"042-8002","student_stateid":"","subject":"Math","course":"Math K-12","growthmeasureyn":"","normsreferencedata":"2025","wiselectedayfall":"","wiselectedaywinter":"20","wiselectedayspring":"","wipreviousayfall":"","wipreviousaywinter":"","wipreviousayspring":"","testtype":"Survey With Goals","testname":"Growth: Math 2-5 CCSS 2010 1.1","testid":"","teststartdate":"2026-02-03","teststarttime":"09:10:08","testdurationminutes":"29","testritscore":"203","teststandarderror":"3.27","testpercentile":"47","achievementquintile":"Avg","percentcorrect":"55","rapidguessingpercentage":"0.0","falltofallprojectedgrowth":"","falltofallobservedgrowth":"","falltofallobservedgrowthse":"","falltofallmetprojectedgrowth":"","falltofallconditionalgrowthindex":"","falltofallconditionalgrowthpercentile":"","falltofallgrowthquintile":"","falltowinterprojectedgrowth":"","falltowinterobservedgrowth":"","falltowinterobservedgrowthse":"","falltowintermetprojectedgrowth":"","falltowinterconditionalgrowthindex":"","falltowinterconditionalgrowthpercentile":"","falltowintergrowthquintile":"","falltospringprojectedgrowth":"","falltospringobservedgrowth":"","falltospringobservedgrowthse":"","falltospringmetprojectedgrowth":"","falltospringconditionalgrowthindex":"","falltospringconditionalgrowthpercentile":"","falltospringgrowthquintile":"","wintertowinterprojectedgrowth":"","wintertowinterobservedgrowth":"","wintertowinterobservedgrowthse":"","wintertowintermetprojectedgrowth":"","wintertowinterconditionalgrowthindex":"","wintertowinterconditionalgrowthpercentile":"","wintertowintergrowthquintile":"","wintertospringprojectedgrowth":"","wintertospringobservedgrowth":"","wintertospringobservedgrowthse":"","wintertospringmetprojectedgrowth":"","wintertospringconditionalgrowthindex":"","wintertospringconditionalgrowthpercentile":"","wintertospringgrowthquintile":"","springtospringprojectedgrowth":"","springtospringobservedgrowth":"","springtospringobservedgrowthse":"","springtospringmetprojectedgrowth":"","springtospringconditionalgrowthindex":"","springtospringconditionalgrowthpercentile":"","springtospringgrowthquintile":"","lexilescore":"","lexilemin":"","lexilemax":"","quantilescore":"520Q","quantilemin":"470Q","quantilemax":"570Q","goal1name":"Operations and Algebraic Thinking","goal1ritscore":"195.0","goal1stderr":"6.7","goal1range":"188-202","goal1adjective":"LoAvg","goal2name":"Number and Operations","goal2ritscore":"201.0","goal2stderr":"5.7","goal2range":"195-207","goal2adjective":"Avg","goal3name":"Measurement and Data","goal3ritscore":"210.0","goal3stderr":"6.9","goal3range":"203-217","goal3adjective":"HiAvg","goal4name":"Geometry","goal4ritscore":"207","goal4stderr":"8.9","goal4range":"198-216","goal4adjective":"Avg","goal5name":"","goal5ritscore":"","goal5stderr":"","goal5range":"","goal5adjective":"","goal6name":"","goal6ritscore":"","goal6stderr":"","goal6range":"","goal6adjective":"","goal7name":"","goal7ritscore":"","goal7stderr":"","goal7range":"","goal7adjective":"","goal8name":"","goal8ritscore":"","goal8stderr":"","goal8range":"","goal8adjective":"","typicalfalltofallgrowth":"","typicalfalltowintergrowth":"","typicalfalltospringgrowth":"","typicalwintertowintergrowth":"8.0","typicalwintertospringgrowth":"6.0","typicalspringtospringgrowth":"","projectedproficiencystudy1":"","projectedproficiencylevel1":"","projectedproficiencystudy2":"","projectedproficiencylevel2":"","projectedproficiencystudy3":"STAAR","projectedproficiencylevel3":"Approaches","projectedproficiencystudy4":"","projectedproficiencylevel4":"","projectedproficiencystudy5":"","projectedproficiencylevel5":"","projectedproficiencystudy6":"","projectedproficiencylevel6":"","projectedproficiencystudy7":"","projectedproficiencylevel7":"","projectedproficiencystudy8":"","projectedproficiencylevel8":"","projectedproficiencystudy9":"","projectedproficiencylevel9":"","projectedproficiencystudy10":"","projectedproficiencylevel10":"","classname":"2","teachername":"Beckley, Kristen","teacherid":"AssessAlpha","teacher_stateid":"","studentlastname":"Sadowsky","studentfirstname":"Ariella","studentmi":"","studentdateofbirth":"2016-05-19","studentethnicgroup":"Not Specified or Other","nweastandard_ethnicgroup":"Not Specified or Other","studentgender":"F","grade":"4","nweastandard_grade":"4","learningrate":"","termprojectedgrowth":"","termobservedgrowth":"","teststartdatelatestinterm":"","minstandarderror":""},{"termname":"Winter 2025-2026","districtname":"Alpha","district_stateid":"","schoolname":"Alpha Plano","school_stateid":"","studentid":"042-8167","student_stateid":"","subject":"Math","course":"Math K-12","growthmeasureyn":"","normsreferencedata":"2025","wiselectedayfall":"","wiselectedaywinter":"20","wiselectedayspring":"","wipreviousayfall":"","wipreviousaywinter":"","wipreviousayspring":"","testtype":"Survey With Goals","testname":"Growth: Math K-2 CCSS 2010 1.1","testid":"","teststartdate":"2026-02-03","teststarttime":"09:03:20","testdurationminutes":"24","testritscore":"186","teststandarderror":"3.34","testpercentile":"99","achievementquintile":"High","percentcorrect":"62","rapidguessingpercentage":"0.0","falltofallprojectedgrowth":"","falltofallobservedgrowth":"","falltofallobservedgrowthse":"","falltofallmetprojectedgrowth":"","falltofallconditionalgrowthindex":"","falltofallconditionalgrowthpercentile":"","falltofallgrowthquintile":"","falltowinterprojectedgrowth":"","falltowinterobservedgrowth":"","falltowinterobservedgrowthse":"","falltowintermetprojectedgrowth":"","falltowinterconditionalgrowthindex":"","falltowinterconditionalgrowthpercentile":"","falltowintergrowthquintile":"","falltospringprojectedgrowth":"","falltospringobservedgrowth":"","falltospringobservedgrowthse":"","falltospringmetprojectedgrowth":"","falltospringconditionalgrowthindex":"","falltospringconditionalgrowthpercentile":"","falltospringgrowthquintile":"","wintertowinterprojectedgrowth":"","wintertowinterobservedgrowth":"","wintertowinterobservedgrowthse":"","wintertowintermetprojectedgrowth":"","wintertowinterconditionalgrowthindex":"","wintertowinterconditionalgrowthpercentile":"","wintertowintergrowthquintile":"","wintertospringprojectedgrowth":"","wintertospringobservedgrowth":"","wintertospringobservedgrowthse":"","wintertospringmetprojectedgrowth":"","wintertospringconditionalgrowthindex":"","wintertospringconditionalgrowthpercentile":"","wintertospringgrowthquintile":"","springtospringprojectedgrowth":"","springtospringobservedgrowth":"","springtospringobservedgrowthse":"","springtospringmetprojectedgrowth":"","springtospringconditionalgrowthindex":"","springtospringconditionalgrowthpercentile":"","springtospringgrowthquintile":"","lexilescore":"","lexilemin":"","lexilemax":"","quantilescore":"230Q","quantilemin":"180Q","quantilemax":"280Q","goal1name":"Operations and Algebraic Thinking","goal1ritscore":"181.0","goal1stderr":"6.0","goal1range":"175-187","goal1adjective":"High","goal2name":"Number and Operations","goal2ritscore":"184.0","goal2stderr":"6.1","goal2range":"178-190","goal2adjective":"High","goal3name":"Measurement and Data","goal3ritscore":"190.0","goal3stderr":"6.3","goal3range":"184-196","goal3adjective":"High","goal4name":"Geometry","goal4ritscore":"194","goal4stderr":"11.5","goal4range":"182-206","goal4adjective":"High","goal5name":"","goal5ritscore":"","goal5stderr":"","goal5range":"","goal5adjective":"","goal6name":"","goal6ritscore":"","goal6stderr":"","goal6range":"","goal6adjective":"","goal7name":"","goal7ritscore":"","goal7stderr":"","goal7range":"","goal7adjective":"","goal8name":"","goal8ritscore":"","goal8stderr":"","goal8range":"","goal8adjective":"","typicalfalltofallgrowth":"","typicalfalltowintergrowth":"","typicalfalltospringgrowth":"","typicalwintertowintergrowth":"12.0","typicalwintertospringgrowth":"1.0","typicalspringtospringgrowth":"","projectedproficiencystudy1":"","projectedproficiencylevel1":"","projectedproficiencystudy2":"","projectedproficiencylevel2":"","projectedproficiencystudy3":"","projectedproficiencylevel3":"","projectedproficiencystudy4":"","projectedproficiencylevel4":"","projectedproficiencystudy5":"","projectedproficiencylevel5":"","projectedproficiencystudy6":"","projectedproficiencylevel6":"","projectedproficiencystudy7":"","projectedproficiencylevel7":"","projectedproficiencystudy8":"","projectedproficiencylevel8":"","projectedproficiencystudy9":"","projectedproficiencylevel9":"","projectedproficiencystudy10":"","projectedproficiencylevel10":"","classname":"0","teachername":"Beckley, Kristen","teacherid":"AssessAlpha","teacher_stateid":"","studentlastname":"Stanton","studentfirstname":"Ronin","studentmi":"","studentdateofbirth":"2020-04-09","studentethnicgroup":"Not Specified or Other","nweastandard_ethnicgroup":"Not Specified or Other","studentgender":"M","grade":"K","nweastandard_grade":"K","learningrate":"","termprojectedgrowth":"","termobservedgrowth":"","teststartdatelatestinterm":"","minstandarderror":""}]