[{"termname":"Fall 2025-2026","districtname":"Alpha","district_stateid":"","schoolname":"Alpha West Palm Beach","school_stateid":"","studentid":"022-1250","student_stateid":"","subject":"Science","course":"Science K-12","growthmeasureyn":"","normsreferencedata":"2025","wiselectedayfall":"1","wiselectedaywinter":"","wiselectedayspring":"","wipreviousayfall":"","wipreviousaywinter":"","wipreviousayspring":"","testtype":"Survey With Goals","testname":"Growth: Science 2-5: for use with NGSS 2013 1.1","testid":"","teststartdate":"2025-08-29","teststarttime":"8:21:32","testdurationminutes":"100","testritscore":"194","teststandarderror":"3.29","testpercentile":"71","achievementquintile":"HiAvg","percentcorrect":"53","rapidguessingpercentage":"0.0","falltofallprojectedgrowth":"","falltofallobservedgrowth":"","falltofallobservedgrowthse":"","falltofallmetprojectedgrowth":"","falltofallconditionalgrowthindex":"","falltofallconditionalgrowthpercentile":"","falltofallgrowthquintile":"","falltowinterprojectedgrowth":"","falltowinterobservedgrowth":"","falltowinterobservedgrowthse":"","falltowintermetprojectedgrowth":"","falltowinterconditionalgrowthindex":"","falltowinterconditionalgrowthpercentile":"","falltowintergrowthquintile":"","falltospringprojectedgrowth":"","falltospringobservedgrowth":"","falltospringobservedgrowthse":"","falltospringmetprojectedgrowth":"","falltospringconditionalgrowthindex":"","falltospringconditionalgrowthpercentile":"","falltospringgrowthquintile":"","wintertowinterprojectedgrowth":"","wintertowinterobservedgrowth":"","wintertowinterobservedgrowthse":"","wintertowintermetprojectedgrowth":"","wintertowinterconditionalgrowthindex":"","wintertowinterconditionalgrowthpercentile":"","wintertowintergrowthquintile":"","wintertospringprojectedgrowth":"","wintertospringobservedgrowth":"","wintertospringobservedgrowthse":"","wintertospringmetprojectedgrowth":"","wintertospringconditionalgrowthindex":"","wintertospringconditionalgrowthpercentile":"","wintertospringgrowthquintile":"","springtospringprojectedgrowth":"","springtospringobservedgrowth":"","springtospringobservedgrowthse":"","springtospringmetprojectedgrowth":"","springtospringconditionalgrowthindex":"","springtospringconditionalgrowthpercentile":"","springtospringgrowthquintile":"","lexilescore":"","lexilemin":"","lexilemax":"","quantilescore":"","quantilemin":"","quantilemax":"","goal1name":"Life Science","goal1ritscore":"204.0","goal1stderr":"6.0","goal1range":"198-210","goal1adjective":"High","goal2name":"Physical Science","goal2ritscore":"194.0","goal2stderr":"5.9","goal2range":"188-200","goal2adjective":"HiAvg","goal3name":"Earth and Space Science","goal3ritscore":"185.0","goal3stderr":"6.3","goal3range":"179-191","goal3adjective":"Avg","goal4name":"","goal4ritscore":"","goal4stderr":"","goal4range":"","goal4adjective":"","goal5name":"","goal5ritscore":"","goal5stderr":"","goal5range":"","goal5adjective":"","goal6name":"","goal6ritscore":"","goal6stderr":"","goal6range":"","goal6adjective":"","goal7name":"","goal7ritscore":"","goal7stderr":"","goal7range":"","goal7adjective":"","goal8name":"","goal8ritscore":"","goal8stderr":"","goal8range":"","goal8adjective":"","typicalfalltofallgrowth":"7","typicalfalltowintergrowth":"3","typicalfalltospringgrowth":"6","typicalwintertowintergrowth":"","typicalwintertospringgrowth":"","typicalspringtospringgrowth":"","projectedproficiencystudy1":"","projectedproficiencylevel1":"","projectedproficiencystudy2":"","projectedproficiencylevel2":"","projectedproficiencystudy3":"","projectedproficiencylevel3":"","projectedproficiencystudy4":"","projectedproficiencylevel4":"","projectedproficiencystudy5":"","projectedproficiencylevel5":"","projectedproficiencystudy6":"","projectedproficiencylevel6":"","projectedproficiencystudy7":"","projectedproficiencylevel7":"","projectedproficiencystudy8":"","projectedproficiencylevel8":"","projectedproficiencystudy9":"","projectedproficiencylevel9":"","projectedproficiencystudy10":"","projectedproficiencylevel10":"","classname":"1","teachername":"Beckley, Kristen","teacherid":"AssessAlpha","teacher_stateid":"","studentlastname":"Grunow","studentfirstname":"Hope","studentmi":"","studentdateofbirth":"2017-01-24","studentethnicgroup":"Not Specified or Other","nweastandard_ethnicgroup":"Not Specified or Other","studentgender":"F","grade":"3","nweastandard_grade":"3","learningrate":"","termprojectedgrowth":"","termobservedgrowth":"","teststartdatelatestinterm":"","minstandarderror":""},{"termname":"Fall 2025-2026","districtname":"Alpha","district_stateid":"","schoolname":"Alpha West Palm Beach","school_stateid":"","studentid":"022-1251","student_stateid":"","subject":"Science","course":"Science K-12","growthmeasureyn":"","normsreferencedata":"2025","wiselectedayfall":"1","wiselectedaywinter":"","wiselectedayspring":"","wipreviousayfall":"","wipreviousaywinter":"","wipreviousayspring":"","testtype":"Survey With Goals","testname":"Growth: Science 2-5: for use with NGSS 2013 1.1","testid":"","teststartdate":"2025-08-22","teststarttime":"12:44:55","testdurationminutes":"77","testritscore":"206","teststandarderror":"3.28","testpercentile":"82","achievementquintile":"High","percentcorrect":"50","rapidguessingpercentage":"0.0","falltofallprojectedgrowth":"","falltofallobservedgrowth":"","falltofallobservedgrowthse":"","falltofallmetprojectedgrowth":"","falltofallconditionalgrowthindex":"","falltofallconditionalgrowthpercentile":"","falltofallgrowthquintile":"","falltowinterprojectedgrowth":"","falltowinterobservedgrowth":"","falltowinterobservedgrowthse":"","falltowintermetprojectedgrowth":"","falltowinterconditionalgrowthindex":"","falltowinterconditionalgrowthpercentile":"","falltowintergrowthquintile":"","falltospringprojectedgrowth":"","falltospringobservedgrowth":"","falltospringobservedgrowthse":"","falltospringmetprojectedgrowth":"","falltospringconditionalgrowthindex":"","falltospringconditionalgrowthpercentile":"","falltospringgrowthquintile":"","wintertowinterprojectedgrowth":"","wintertowinterobservedgrowth":"","wintertowinterobservedgrowthse":"","wintertowintermetprojectedgrowth":"","wintertowinterconditionalgrowthindex":"","wintertowinterconditionalgrowthpercentile":"","wintertowintergrowthquintile":"","wintertospringprojectedgrowth":"","wintertospringobservedgrowth":"","wintertospringobservedgrowthse":"","wintertospringmetprojectedgrowth":"","wintertospringconditionalgrowthindex":"","wintertospringconditionalgrowthpercentile":"","wintertospringgrowthquintile":"","springtospringprojectedgrowth":"","springtospringobservedgrowth":"","springtospringobservedgrowthse":"","springtospringmetprojectedgrowth":"","springtospringconditionalgrowthindex":"","springtospringconditionalgrowthpercentile":"","springtospringgrowthquintile":"","lexilescore":"","lexilemin":"","lexilemax":"","quantilescore":"","quantilemin":"","quantilemax":"","goal1name":"Life Science","goal1ritscore":"203.0","goal1stderr":"5.5","goal1range":"197-209","goal1adjective":"HiAvg","goal2name":"Physical Science","goal2ritscore":"202.0","goal2stderr":"5.8","goal2range":"196-208","goal2adjective":"HiAvg","goal3name":"Earth and Space Science","goal3ritscore":"214.0","goal3stderr":"5.9","goal3range":"208-220","goal3adjective":"High","goal4name":"","goal4ritscore":"","goal4stderr":"","goal4range":"","goal4adjective":"","goal5name":"","goal5ritscore":"","goal5stderr":"","goal5range":"","goal5adjective":"","goal6name":"","goal6ritscore":"","goal6stderr":"","goal6range":"","goal6adjective":"","goal7name":"","goal7ritscore":"","goal7stderr":"","goal7range":"","goal7adjective":"","goal8name":"","goal8ritscore":"","goal8stderr":"","goal8range":"","goal8adjective":"","typicalfalltofallgrowth":"5","typicalfalltowintergrowth":"2","typicalfalltospringgrowth":"4","typicalwintertowintergrowth":"","typicalwintertospringgrowth":"","typicalspringtospringgrowth":"","projectedproficiencystudy1":"","projectedproficiencylevel1":"","projectedproficiencystudy2":"","projectedproficiencylevel2":"","projectedproficiencystudy3":"","projectedproficiencylevel3":"","projectedproficiencystudy4":"","projectedproficiencylevel4":"","projectedproficiencystudy5":"","projectedproficiencylevel5":"","projectedproficiencystudy6":"","projectedproficiencylevel6":"","projectedproficiencystudy7":"","projectedproficiencylevel7":"","projectedproficiencystudy8":"","projectedproficiencylevel8":"","projectedproficiencystudy9":"","projectedproficiencylevel9":"","projectedproficiencystudy10":"","projectedproficiencylevel10":"","classname":"2","teachername":"Beckley, Kristen","teacherid":"AssessAlpha","teacher_stateid":"","studentlastname":"Grunow","studentfirstname":"Johnny","studentmi":"","studentdateofbirth":"2015-12-01","studentethnicgroup":"Not Specified or Other","nweastandard_ethnicgroup":"Not Specified or Other","studentgender":"M","grade":"4","nweastandard_grade":"4","learningrate":"","termprojectedgrowth":"","termobservedgrowth":"","teststartdatelatestinterm":"","minstandarderror":""},{"termname":"Fall 2025-2026","districtname":"Alpha","district_stateid":"","schoolname":"Alpha West Palm Beach","school_stateid":"","studentid":"022-1250","student_stateid":"","subject":"Language","course":"Language Usage","growthmeasureyn":"","normsreferencedata":"2025","wiselectedayfall":"1","wiselectedaywinter":"","wiselectedayspring":"","wipreviousayfall":"","wipreviousaywinter":"","wipreviousayspring":"","testtype":"Survey With Goals","testname":"Growth: Language 2+ CCSS 2010 1.1","testid":"","teststartdate":"2025-08-21","teststarttime":"12:57:17","testdurationminutes":"62","testritscore":"197","teststandarderror":"3.26","testpercentile":"78","achievementquintile":"HiAvg","percentcorrect":"51","rapidguessingpercentage":"0.0","falltofallprojectedgrowth":"","falltofallobservedgrowth":"","falltofallobservedgrowthse":"","falltofallmetprojectedgrowth":"","falltofallconditionalgrowthindex":"","falltofallconditionalgrowthpercentile":"","falltofallgrowthquintile":"","falltowinterprojectedgrowth":"","falltowinterobservedgrowth":"","falltowinterobservedgrowthse":"","falltowintermetprojectedgrowth":"","falltowinterconditionalgrowthindex":"","falltowinterconditionalgrowthpercentile":"","falltowintergrowthquintile":"","falltospringprojectedgrowth":"","falltospringobservedgrowth":"","falltospringobservedgrowthse":"","falltospringmetprojectedgrowth":"","falltospringconditionalgrowthindex":"","falltospringconditionalgrowthpercentile":"","falltospringgrowthquintile":"","wintertowinterprojectedgrowth":"","wintertowinterobservedgrowth":"","wintertowinterobservedgrowthse":"","wintertowintermetprojectedgrowth":"","wintertowinterconditionalgrowthindex":"","wintertowinterconditionalgrowthpercentile":"","wintertowintergrowthquintile":"","wintertospringprojectedgrowth":"","wintertospringobservedgrowth":"","wintertospringobservedgrowthse":"","wintertospringmetprojectedgrowth":"","wintertospringconditionalgrowthindex":"","wintertospringconditionalgrowthpercentile":"","wintertospringgrowthquintile":"","springtospringprojectedgrowth":"","springtospringobservedgrowth":"","springtospringobservedgrowthse":"","springtospringmetprojectedgrowth":"","springtospringconditionalgrowthindex":"","springtospringconditionalgrowthpercentile":"","springtospringgrowthquintile":"","lexilescore":"","lexilemin":"","lexilemax":"","quantilescore":"","quantilemin":"","quantilemax":"","goal1name":"Writing: Write, Revise Texts for Purpose and Audience","goal1ritscore":"200.0","goal1stderr":"5.9","goal1range":"194-206","goal1adjective":"High","goal2name":"Language: Understand, Edit for Grammar, Usage","goal2ritscore":"205.0","goal2stderr":"5.8","goal2range":"199-211","goal2adjective":"High","goal3name":"Language: Understand, Edit for Mechanics","goal3ritscore":"186.0","goal3stderr":"6.0","goal3range":"180-192","goal3adjective":"Avg","goal4name":"","goal4ritscore":"","goal4stderr":"","goal4range":"","goal4adjective":"","goal5name":"","goal5ritscore":"","goal5stderr":"","goal5range":"","goal5adjective":"","goal6name":"","goal6ritscore":"","goal6stderr":"","goal6range":"","goal6adjective":"","goal7name":"","goal7ritscore":"","goal7stderr":"","goal7range":"","goal7adjective":"","goal8name":"","goal8ritscore":"","goal8stderr":"","goal8range":"","goal8adjective":"","typicalfalltofallgrowth":"9","typicalfalltowintergrowth":"4","typicalfalltospringgrowth":"8","typicalwintertowintergrowth":"","typicalwintertospringgrowth":"","typicalspringtospringgrowth":"","projectedproficiencystudy1":"","projectedproficiencylevel1":"","projectedproficiencystudy2":"","projectedproficiencylevel2":"","projectedproficiencystudy3":"","projectedproficiencylevel3":"","projectedproficiencystudy4":"","projectedproficiencylevel4":"","projectedproficiencystudy5":"","projectedproficiencylevel5":"","projectedproficiencystudy6":"","projectedproficiencylevel6":"","projectedproficiencystudy7":"","projectedproficiencylevel7":"","projectedproficiencystudy8":"","projectedproficiencylevel8":"","projectedproficiencystudy9":"","projectedproficiencylevel9":"","projectedproficiencystudy10":"","projectedproficiencylevel10":"","classname":"1","teachername":"Beckley, Kristen","teacherid":"AssessAlpha","teacher_stateid":"","studentlastname":"Grunow","studentfirstname":"Hope","studentmi":"","studentdateofbirth":"2017-01-24","studentethnicgroup":"Not Specified or Other","nweastandard_ethnicgroup":"Not Specified or Other","studentgender":"F","grade":"3","nweastandard_grade":"3","learningrate":"","termprojectedgrowth":"","termobservedgrowth":"","teststartdatelatestinterm":"","minstandarderror":""},{"termname":"Fall 2025-2026","districtname":"Alpha","district_stateid":"","schoolname":"Alpha West Palm Beach","school_stateid":"","studentid":"022-1251","student_stateid":"","subject":"Language","course":"Language Usage","growthmeasureyn":"","normsreferencedata":"2025","wiselectedayfall":"1","wiselectedaywinter":"","wiselectedayspring":"","wipreviousayfall":"","wipreviousaywinter":"","wipreviousayspring":"","testtype":"Survey With Goals","testname":"Growth: Language 2+ CCSS 2010 1.1","testid":"","teststartdate":"2025-08-21","teststarttime":"8:42:00","testdurationminutes":"53","testritscore":"200","teststandarderror":"3.27","testpercentile":"64","achievementquintile":"HiAvg","percentcorrect":"56","rapidguessingpercentage":"0.0","falltofallprojectedgrowth":"","falltofallobservedgrowth":"","falltofallobservedgrowthse":"","falltofallmetprojectedgrowth":"","falltofallconditionalgrowthindex":"","falltofallconditionalgrowthpercentile":"","falltofallgrowthquintile":"","falltowinterprojectedgrowth":"","falltowinterobservedgrowth":"","falltowinterobservedgrowthse":"","falltowintermetprojectedgrowth":"","falltowinterconditionalgrowthindex":"","falltowinterconditionalgrowthpercentile":"","falltowintergrowthquintile":"","falltospringprojectedgrowth":"","falltospringobservedgrowth":"","falltospringobservedgrowthse":"","falltospringmetprojectedgrowth":"","falltospringconditionalgrowthindex":"","falltospringconditionalgrowthpercentile":"","falltospringgrowthquintile":"","wintertowinterprojectedgrowth":"","wintertowinterobservedgrowth":"","wintertowinterobservedgrowthse":"","wintertowintermetprojectedgrowth":"","wintertowinterconditionalgrowthindex":"","wintertowinterconditionalgrowthpercentile":"","wintertowintergrowthquintile":"","wintertospringprojectedgrowth":"","wintertospringobservedgrowth":"","wintertospringobservedgrowthse":"","wintertospringmetprojectedgrowth":"","wintertospringconditionalgrowthindex":"","wintertospringconditionalgrowthpercentile":"","wintertospringgrowthquintile":"","springtospringprojectedgrowth":"","springtospringobservedgrowth":"","springtospringobservedgrowthse":"","springtospringmetprojectedgrowth":"","springtospringconditionalgrowthindex":"","springtospringconditionalgrowthpercentile":"","springtospringgrowthquintile":"","lexilescore":"","lexilemin":"","lexilemax":"","quantilescore":"","quantilemin":"","quantilemax":"","goal1name":"Writing: Write, Revise Texts for Purpose and Audience","goal1ritscore":"224.0","goal1stderr":"10.4","goal1range":"214-234","goal1adjective":"High","goal2name":"Language: Understand, Edit for Grammar, Usage","goal2ritscore":"195.0","goal2stderr":"5.7","goal2range":"189-201","goal2adjective":"Avg","goal3name":"Language: Understand, Edit for Mechanics","goal3ritscore":"187.0","goal3stderr":"6.1","goal3range":"181-193","goal3adjective":"LoAvg","goal4name":"","goal4ritscore":"","goal4stderr":"","goal4range":"","goal4adjective":"","goal5name":"","goal5ritscore":"","goal5stderr":"","goal5range":"","goal5adjective":"","goal6name":"","goal6ritscore":"","goal6stderr":"","goal6range":"","goal6adjective":"","goal7name":"","goal7ritscore":"","goal7stderr":"","goal7range":"","goal7adjective":"","goal8name":"","goal8ritscore":"","goal8stderr":"","goal8range":"","goal8adjective":"","typicalfalltofallgrowth":"7","typicalfalltowintergrowth":"4","typicalfalltospringgrowth":"6","typicalwintertowintergrowth":"","typicalwintertospringgrowth":"","typicalspringtospringgrowth":"","projectedproficiencystudy1":"","projectedproficiencylevel1":"","projectedproficiencystudy2":"","projectedproficiencylevel2":"","projectedproficiencystudy3":"","projectedproficiencylevel3":"","projectedproficiencystudy4":"","projectedproficiencylevel4":"","projectedproficiencystudy5":"","projectedproficiencylevel5":"","projectedproficiencystudy6":"","projectedproficiencylevel6":"","projectedproficiencystudy7":"","projectedproficiencylevel7":"","projectedproficiencystudy8":"","projectedproficiencylevel8":"","projectedproficiencystudy9":"","projectedproficiencylevel9":"","projectedproficiencystudy10":"","projectedproficiencylevel10":"","classname":"2","teachername":"Beckley, Kristen","teacherid":"AssessAlpha","teacher_stateid":"","studentlastname":"Grunow","studentfirstname":"Johnny","studentmi":"","studentdateofbirth":"2015-12-01","studentethnicgroup":"Not Specified or Other","nweastandard_ethnicgroup":"Not Specified or Other","studentgender":"M","grade":"4","nweastandard_grade":"4","learningrate":"","termprojectedgrowth":"","termobservedgrowth":"","teststartdatelatestinterm":"","minstandarderror":""},{"termname":"Fall 2025-2026","districtname":"Alpha","district_stateid":"","schoolname":"Alpha West Palm Beach","school_stateid":"","studentid":"022-1899","student_stateid":"","subject":"Language","course":"Language Usage","growthmeasureyn":"","normsreferencedata":"2025","wiselectedayfall":"1","wiselectedaywinter":"","wiselectedayspring":"","wipreviousayfall":"","wipreviousaywinter":"","wipreviousayspring":"","testtype":"Survey With Goals","testname":"Growth: Language 2+ CCSS 2010 1.1","testid":"","teststartdate":"2025-08-21","teststarttime":"8:45:04","testdurationminutes":"21","testritscore":"169","teststandarderror":"3.3","testpercentile":"50","achievementquintile":"Avg","percentcorrect":"43","rapidguessingpercentage":"7.1429","falltofallprojectedgrowth":"","falltofallobservedgrowth":"","falltofallobservedgrowthse":"","falltofallmetprojectedgrowth":"","falltofallconditionalgrowthindex":"","falltofallconditionalgrowthpercentile":"","falltofallgrowthquintile":"","falltowinterprojectedgrowth":"","falltowinterobservedgrowth":"","falltowinterobservedgrowthse":"","falltowintermetprojectedgrowth":"","falltowinterconditionalgrowthindex":"","falltowinterconditionalgrowthpercentile":"","falltowintergrowthquintile":"","falltospringprojectedgrowth":"","falltospringobservedgrowth":"","falltospringobservedgrowthse":"","falltospringmetprojectedgrowth":"","falltospringconditionalgrowthindex":"","falltospringconditionalgrowthpercentile":"","falltospringgrowthquintile":"","wintertowinterprojectedgrowth":"","wintertowinterobservedgrowth":"","wintertowinterobservedgrowthse":"","wintertowintermetprojectedgrowth":"","wintertowinterconditionalgrowthindex":"","wintertowinterconditionalgrowthpercentile":"","wintertowintergrowthquintile":"","wintertospringprojectedgrowth":"","wintertospringobservedgrowth":"","wintertospringobservedgrowthse":"","wintertospringmetprojectedgrowth":"","wintertospringconditionalgrowthindex":"","wintertospringconditionalgrowthpercentile":"","wintertospringgrowthquintile":"","springtospringprojectedgrowth":"","springtospringobservedgrowth":"","springtospringobservedgrowthse":"","springtospringmetprojectedgrowth":"","springtospringconditionalgrowthindex":"","springtospringconditionalgrowthpercentile":"","springtospringgrowthquintile":"","lexilescore":"","lexilemin":"","lexilemax":"","quantilescore":"","quantilemin":"","quantilemax":"","goal1name":"Writing: Write, Revise Texts for Purpose and Audience","goal1ritscore":"164.0","goal1stderr":"5.9","goal1range":"158-170","goal1adjective":"LoAvg","goal2name":"Language: Understand, Edit for Grammar, Usage","goal2ritscore":"169.0","goal2stderr":"5.7","goal2range":"163-175","goal2adjective":"Avg","goal3name":"Language: Understand, Edit for Mechanics","goal3ritscore":"175.0","goal3stderr":"5.6","goal3range":"169-181","goal3adjective":"HiAvg","goal4name":"","goal4ritscore":"","goal4stderr":"","goal4range":"","goal4adjective":"","goal5name":"","goal5ritscore":"","goal5stderr":"","goal5range":"","goal5adjective":"","goal6name":"","goal6ritscore":"","goal6stderr":"","goal6range":"","goal6adjective":"","goal7name":"","goal7ritscore":"","goal7stderr":"","goal7range":"","goal7adjective":"","goal8name":"","goal8ritscore":"","goal8stderr":"","goal8range":"","goal8adjective":"","typicalfalltofallgrowth":"16","typicalfalltowintergrowth":"8","typicalfalltospringgrowth":"14","typicalwintertowintergrowth":"","typicalwintertospringgrowth":"","typicalspringtospringgrowth":"","projectedproficiencystudy1":"","projectedproficiencylevel1":"","projectedproficiencystudy2":"","projectedproficiencylevel2":"","projectedproficiencystudy3":"","projectedproficiencylevel3":"","projectedproficiencystudy4":"","projectedproficiencylevel4":"","projectedproficiencystudy5":"","projectedproficiencylevel5":"","projectedproficiencystudy6":"","projectedproficiencylevel6":"","projectedproficiencystudy7":"","projectedproficiencylevel7":"","projectedproficiencystudy8":"","projectedproficiencylevel8":"","projectedproficiencystudy9":"","projectedproficiencylevel9":"","projectedproficiencystudy10":"","projectedproficiencylevel10":"","classname":"1","teachername":"Beckley, Kristen","teacherid":"AssessAlpha","teacher_stateid":"","studentlastname":"D'Anieri","studentfirstname":"Adriana","studentmi":"","studentdateofbirth":"2018-05-29","studentethnicgroup":"Not Specified or Other","nweastandard_ethnicgroup":"Not Specified or Other","studentgender":"X","grade":"2","nweastandard_grade":"2","learningrate":"","termprojectedgrowth":"","termobservedgrowth":"","teststartdatelatestinterm":"","minstandarderror":""},{"termname":"Fall 2025-2026","districtname":"Alpha","district_stateid":"","schoolname":"Alpha West Palm Beach","school_stateid":"","studentid":"022-1250","student_stateid":"","subject":"Math","course":"Math K-12","growthmeasureyn":"","normsreferencedata":"2025","wiselectedayfall":"1","wiselectedaywinter":"","wiselectedayspring":"","wipreviousayfall":"","wipreviousaywinter":"","wipreviousayspring":"","testtype":"Survey With Goals","testname":"Growth: Math 2-5 CCSS 2010 1.1","testid":"","teststartdate":"2025-08-20","teststarttime":"8:29:02","testdurationminutes":"49","testritscore":"181","teststandarderror":"3.27","testpercentile":"46","achievementquintile":"Avg","percentcorrect":"50","rapidguessingpercentage":"0.0","falltofallprojectedgrowth":"","falltofallobservedgrowth":"","falltofallobservedgrowthse":"","falltofallmetprojectedgrowth":"","falltofallconditionalgrowthindex":"","falltofallconditionalgrowthpercentile":"","falltofallgrowthquintile":"","falltowinterprojectedgrowth":"","falltowinterobservedgrowth":"","falltowinterobservedgrowthse":"","falltowintermetprojectedgrowth":"","falltowinterconditionalgrowthindex":"","falltowinterconditionalgrowthpercentile":"","falltowintergrowthquintile":"","falltospringprojectedgrowth":"","falltospringobservedgrowth":"","falltospringobservedgrowthse":"","falltospringmetprojectedgrowth":"","falltospringconditionalgrowthindex":"","falltospringconditionalgrowthpercentile":"","falltospringgrowthquintile":"","wintertowinterprojectedgrowth":"","wintertowinterobservedgrowth":"","wintertowinterobservedgrowthse":"","wintertowintermetprojectedgrowth":"","wintertowinterconditionalgrowthindex":"","wintertowinterconditionalgrowthpercentile":"","wintertowintergrowthquintile":"","wintertospringprojectedgrowth":"","wintertospringobservedgrowth":"","wintertospringobservedgrowthse":"","wintertospringmetprojectedgrowth":"","wintertospringconditionalgrowthindex":"","wintertospringconditionalgrowthpercentile":"","wintertospringgrowthquintile":"","springtospringprojectedgrowth":"","springtospringobservedgrowth":"","springtospringobservedgrowthse":"","springtospringmetprojectedgrowth":"","springtospringconditionalgrowthindex":"","springtospringconditionalgrowthpercentile":"","springtospringgrowthquintile":"","lexilescore":"","lexilemin":"","lexilemax":"","quantilescore":"140Q","quantilemin":"90Q","quantilemax":"190Q","goal1name":"Operations and Algebraic Thinking","goal1ritscore":"174.0","goal1stderr":"7.0","goal1range":"167-181","goal1adjective":"LoAvg","goal2name":"Number and Operations","goal2ritscore":"189.0","goal2stderr":"6.2","goal2range":"183-195","goal2adjective":"HiAvg","goal3name":"Measurement and Data","goal3ritscore":"175.0","goal3stderr":"6.4","goal3range":"169-181","goal3adjective":"LoAvg","goal4name":"Geometry","goal4ritscore":"191","goal4stderr":"9.2","goal4range":"182-200","goal4adjective":"HiAvg","goal5name":"","goal5ritscore":"","goal5stderr":"","goal5range":"","goal5adjective":"","goal6name":"","goal6ritscore":"","goal6stderr":"","goal6range":"","goal6adjective":"","goal7name":"","goal7ritscore":"","goal7stderr":"","goal7range":"","goal7adjective":"","goal8name":"","goal8ritscore":"","goal8stderr":"","goal8range":"","goal8adjective":"","typicalfalltofallgrowth":"15","typicalfalltowintergrowth":"10","typicalfalltospringgrowth":"17","typicalwintertowintergrowth":"","typicalwintertospringgrowth":"","typicalspringtospringgrowth":"","projectedproficiencystudy1":"","projectedproficiencylevel1":"","projectedproficiencystudy2":"","projectedproficiencylevel2":"","projectedproficiencystudy3":"STAAR","projectedproficiencylevel3":"Approaches","projectedproficiencystudy4":"","projectedproficiencylevel4":"","projectedproficiencystudy5":"","projectedproficiencylevel5":"","projectedproficiencystudy6":"","projectedproficiencylevel6":"","projectedproficiencystudy7":"","projectedproficiencylevel7":"","projectedproficiencystudy8":"","projectedproficiencylevel8":"","projectedproficiencystudy9":"","projectedproficiencylevel9":"","projectedproficiencystudy10":"","projectedproficiencylevel10":"","classname":"1","teachername":"Beckley, Kristen","teacherid":"AssessAlpha","teacher_stateid":"","studentlastname":"Grunow","studentfirstname":"Hope","studentmi":"","studentdateofbirth":"2017-01-24","studentethnicgroup":"Not Specified or Other","nweastandard_ethnicgroup":"Not Specified or Other","studentgender":"F","grade":"3","nweastandard_grade":"3","learningrate":"","termprojectedgrowth":"","termobservedgrowth":"","teststartdatelatestinterm":"","minstandarderror":""},{"termname":"Fall 2025-2026","districtname":"Alpha","district_stateid":"","schoolname":"Alpha West Palm Beach","school_stateid":"","studentid":"022-1251","student_stateid":"","subject":"Math","course":"Math K-12","growthmeasureyn":"","normsreferencedata":"2025","wiselectedayfall":"1","wiselectedaywinter":"","wiselectedayspring":"","wipreviousayfall":"","wipreviousaywinter":"","wipreviousayspring":"","testtype":"Survey With Goals","testname":"Growth: Math 2-5 CCSS 2010 1.1","testid":"","teststartdate":"2025-08-20","teststarttime":"8:29:14","testdurationminutes":"55","testritscore":"194","teststandarderror":"3.31","testpercentile":"46","achievementquintile":"Avg","percentcorrect":"49","rapidguessingpercentage":"0.0","falltofallprojectedgrowth":"","falltofallobservedgrowth":"","falltofallobservedgrowthse":"","falltofallmetprojectedgrowth":"","falltofallconditionalgrowthindex":"","falltofallconditionalgrowthpercentile":"","falltofallgrowthquintile":"","falltowinterprojectedgrowth":"","falltowinterobservedgrowth":"","falltowinterobservedgrowthse":"","falltowintermetprojectedgrowth":"","falltowinterconditionalgrowthindex":"","falltowinterconditionalgrowthpercentile":"","falltowintergrowthquintile":"","falltospringprojectedgrowth":"","falltospringobservedgrowth":"","falltospringobservedgrowthse":"","falltospringmetprojectedgrowth":"","falltospringconditionalgrowthindex":"","falltospringconditionalgrowthpercentile":"","falltospringgrowthquintile":"","wintertowinterprojectedgrowth":"","wintertowinterobservedgrowth":"","wintertowinterobservedgrowthse":"","wintertowintermetprojectedgrowth":"","wintertowinterconditionalgrowthindex":"","wintertowinterconditionalgrowthpercentile":"","wintertowintergrowthquintile":"","wintertospringprojectedgrowth":"","wintertospringobservedgrowth":"","wintertospringobservedgrowthse":"","wintertospringmetprojectedgrowth":"","wintertospringconditionalgrowthindex":"","wintertospringconditionalgrowthpercentile":"","wintertospringgrowthquintile":"","springtospringprojectedgrowth":"","springtospringobservedgrowth":"","springtospringobservedgrowthse":"","springtospringmetprojectedgrowth":"","springtospringconditionalgrowthindex":"","springtospringconditionalgrowthpercentile":"","springtospringgrowthquintile":"","lexilescore":"","lexilemin":"","lexilemax":"","quantilescore":"365Q","quantilemin":"315Q","quantilemax":"415Q","goal1name":"Operations and Algebraic Thinking","goal1ritscore":"198.0","goal1stderr":"6.2","goal1range":"192-204","goal1adjective":"Avg","goal2name":"Number and Operations","goal2ritscore":"188.0","goal2stderr":"5.7","goal2range":"182-194","goal2adjective":"LoAvg","goal3name":"Measurement and Data","goal3ritscore":"193.0","goal3stderr":"6.7","goal3range":"186-200","goal3adjective":"Avg","goal4name":"Geometry","goal4ritscore":"201","goal4stderr":"8.5","goal4range":"193-209","goal4adjective":"HiAvg","goal5name":"","goal5ritscore":"","goal5stderr":"","goal5range":"","goal5adjective":"","goal6name":"","goal6ritscore":"","goal6stderr":"","goal6range":"","goal6adjective":"","goal7name":"","goal7ritscore":"","goal7stderr":"","goal7range":"","goal7adjective":"","goal8name":"","goal8ritscore":"","goal8stderr":"","goal8range":"","goal8adjective":"","typicalfalltofallgrowth":"12","typicalfalltowintergrowth":"9","typicalfalltospringgrowth":"14","typicalwintertowintergrowth":"","typicalwintertospringgrowth":"","typicalspringtospringgrowth":"","projectedproficiencystudy1":"","projectedproficiencylevel1":"","projectedproficiencystudy2":"","projectedproficiencylevel2":"","projectedproficiencystudy3":"STAAR","projectedproficiencylevel3":"Did Not Meet","projectedproficiencystudy4":"","projectedproficiencylevel4":"","projectedproficiencystudy5":"","projectedproficiencylevel5":"","projectedproficiencystudy6":"","projectedproficiencylevel6":"","projectedproficiencystudy7":"","projectedproficiencylevel7":"","projectedproficiencystudy8":"","projectedproficiencylevel8":"","projectedproficiencystudy9":"","projectedproficiencylevel9":"","projectedproficiencystudy10":"","projectedproficiencylevel10":"","classname":"2","teachername":"Beckley, Kristen","teacherid":"AssessAlpha","teacher_stateid":"","studentlastname":"Grunow","studentfirstname":"Johnny","studentmi":"","studentdateofbirth":"2015-12-01","studentethnicgroup":"Not Specified or Other","nweastandard_ethnicgroup":"Not Specified or Other","studentgender":"M","grade":"4","nweastandard_grade":"4","learningrate":"","termprojectedgrowth":"","termobservedgrowth":"","teststartdatelatestinterm":"","minstandarderror":""},{"termname":"Fall 2025-2026","districtname":"Alpha","district_stateid":"","schoolname":"Alpha West Palm Beach","school_stateid":"","studentid":"022-1840","student_stateid":"","subject":"Math","course":"Math K-12","growthmeasureyn":"","normsreferencedata":"2025","wiselectedayfall":"1","wiselectedaywinter":"","wiselectedayspring":"","wipreviousayfall":"","wipreviousaywinter":"","wipreviousayspring":"","testtype":"Survey With Goals","testname":"Growth: Math K-2 CCSS 2010 1.1","testid":"","teststartdate":"2025-08-20","teststarttime":"8:28:33","testdurationminutes":"40","testritscore":"141","teststandarderror":"3.13","testpercentile":"55","achievementquintile":"Avg","percentcorrect":"47","rapidguessingpercentage":"0.0","falltofallprojectedgrowth":"","falltofallobservedgrowth":"","falltofallobservedgrowthse":"","falltofallmetprojectedgrowth":"","falltofallconditionalgrowthindex":"","falltofallconditionalgrowthpercentile":"","falltofallgrowthquintile":"","falltowinterprojectedgrowth":"","falltowinterobservedgrowth":"","falltowinterobservedgrowthse":"","falltowintermetprojectedgrowth":"","falltowinterconditionalgrowthindex":"","falltowinterconditionalgrowthpercentile":"","falltowintergrowthquintile":"","falltospringprojectedgrowth":"","falltospringobservedgrowth":"","falltospringobservedgrowthse":"","falltospringmetprojectedgrowth":"","falltospringconditionalgrowthindex":"","falltospringconditionalgrowthpercentile":"","falltospringgrowthquintile":"","wintertowinterprojectedgrowth":"","wintertowinterobservedgrowth":"","wintertowinterobservedgrowthse":"","wintertowintermetprojectedgrowth":"","wintertowinterconditionalgrowthindex":"","wintertowinterconditionalgrowthpercentile":"","wintertowintergrowthquintile":"","wintertospringprojectedgrowth":"","wintertospringobservedgrowth":"","wintertospringobservedgrowthse":"","wintertospringmetprojectedgrowth":"","wintertospringconditionalgrowthindex":"","wintertospringconditionalgrowthpercentile":"","wintertospringgrowthquintile":"","springtospringprojectedgrowth":"","springtospringobservedgrowth":"","springtospringobservedgrowthse":"","springtospringmetprojectedgrowth":"","springtospringconditionalgrowthindex":"","springtospringconditionalgrowthpercentile":"","springtospringgrowthquintile":"","lexilescore":"","lexilemin":"","lexilemax":"","quantilescore":"EM400Q","quantilemin":"EM400Q","quantilemax":"EM400Q","goal1name":"Operations and Algebraic Thinking","goal1ritscore":"139.0","goal1stderr":"6.2","goal1range":"133-145","goal1adjective":"Avg","goal2name":"Number and Operations","goal2ritscore":"139.0","goal2stderr":"5.7","goal2range":"133-145","goal2adjective":"Avg","goal3name":"Measurement and Data","goal3ritscore":"146.0","goal3stderr":"6.0","goal3range":"140-152","goal3adjective":"HiAvg","goal4name":"Geometry","goal4ritscore":"139","goal4stderr":"8.3","goal4range":"131-147","goal4adjective":"Avg","goal5name":"","goal5ritscore":"","goal5stderr":"","goal5range":"","goal5adjective":"","goal6name":"","goal6ritscore":"","goal6stderr":"","goal6range":"","goal6adjective":"","goal7name":"","goal7ritscore":"","goal7stderr":"","goal7range":"","goal7adjective":"","goal8name":"","goal8ritscore":"","goal8stderr":"","goal8range":"","goal8adjective":"","typicalfalltofallgrowth":"20","typicalfalltowintergrowth":"11","typicalfalltospringgrowth":"18","typicalwintertowintergrowth":"","typicalwintertospringgrowth":"","typicalspringtospringgrowth":"","projectedproficiencystudy1":"","projectedproficiencylevel1":"","projectedproficiencystudy2":"","projectedproficiencylevel2":"","projectedproficiencystudy3":"","projectedproficiencylevel3":"","projectedproficiencystudy4":"","projectedproficiencylevel4":"","projectedproficiencystudy5":"","projectedproficiencylevel5":"","projectedproficiencystudy6":"","projectedproficiencylevel6":"","projectedproficiencystudy7":"","projectedproficiencylevel7":"","projectedproficiencystudy8":"","projectedproficiencylevel8":"","projectedproficiencystudy9":"","projectedproficiencylevel9":"","projectedproficiencystudy10":"","projectedproficiencylevel10":"","classname":"0","teachername":"Beckley, Kristen","teacherid":"AssessAlpha","teacher_stateid":"","studentlastname":"Grunow","studentfirstname":"Elizabeth","studentmi":"","studentdateofbirth":"2020-06-02","studentethnicgroup":"Not Specified or Other","nweastandard_ethnicgroup":"Not Specified or Other","studentgender":"F","grade":"K","nweastandard_grade":"K","learningrate":"","termprojectedgrowth":"","termobservedgrowth":"","teststartdatelatestinterm":"","minstandarderror":""},{"termname":"Fall 2025-2026","districtname":"Alpha","district_stateid":"","schoolname":"Alpha West Palm Beach","school_stateid":"","studentid":"022-1899","student_stateid":"","subject":"Math","course":"Math K-12","growthmeasureyn":"","normsreferencedata":"2025","wiselectedayfall":"1","wiselectedaywinter":"","wiselectedayspring":"","wipreviousayfall":"","wipreviousaywinter":"","wipreviousayspring":"","testtype":"Survey With Goals","testname":"Growth: Math 2-5 CCSS 2010 1.1","testid":"","teststartdate":"2025-08-20","teststarttime":"8:28:16","testdurationminutes":"41","testritscore":"171","teststandarderror":"3.3","testpercentile":"49","achievementquintile":"Avg","percentcorrect":"45","rapidguessingpercentage":"0.0","falltofallprojectedgrowth":"","falltofallobservedgrowth":"","falltofallobservedgrowthse":"","falltofallmetprojectedgrowth":"","falltofallconditionalgrowthindex":"","falltofallconditionalgrowthpercentile":"","falltofallgrowthquintile":"","falltowinterprojectedgrowth":"","falltowinterobservedgrowth":"","falltowinterobservedgrowthse":"","falltowintermetprojectedgrowth":"","falltowinterconditionalgrowthindex":"","falltowinterconditionalgrowthpercentile":"","falltowintergrowthquintile":"","falltospringprojectedgrowth":"","falltospringobservedgrowth":"","falltospringobservedgrowthse":"","falltospringmetprojectedgrowth":"","falltospringconditionalgrowthindex":"","falltospringconditionalgrowthpercentile":"","falltospringgrowthquintile":"","wintertowinterprojectedgrowth":"","wintertowinterobservedgrowth":"","wintertowinterobservedgrowthse":"","wintertowintermetprojectedgrowth":"","wintertowinterconditionalgrowthindex":"","wintertowinterconditionalgrowthpercentile":"","wintertowintergrowthquintile":"","wintertospringprojectedgrowth":"","wintertospringobservedgrowth":"","wintertospringobservedgrowthse":"","wintertospringmetprojectedgrowth":"","wintertospringconditionalgrowthindex":"","wintertospringconditionalgrowthpercentile":"","wintertospringgrowthquintile":"","springtospringprojectedgrowth":"","springtospringobservedgrowth":"","springtospringobservedgrowthse":"","springtospringmetprojectedgrowth":"","springtospringconditionalgrowthindex":"","springtospringconditionalgrowthpercentile":"","springtospringgrowthquintile":"","lexilescore":"","lexilemin":"","lexilemax":"","quantilescore":"EM30Q","quantilemin":"EM80Q","quantilemax":"20Q","goal1name":"Operations and Algebraic Thinking","goal1ritscore":"164.0","goal1stderr":"7.0","goal1range":"157-171","goal1adjective":"LoAvg","goal2name":"Number and Operations","goal2ritscore":"175.0","goal2stderr":"5.7","goal2range":"169-181","goal2adjective":"Avg","goal3name":"Measurement and Data","goal3ritscore":"167.0","goal3stderr":"6.7","goal3range":"160-174","goal3adjective":"LoAvg","goal4name":"Geometry","goal4ritscore":"183","goal4stderr":"9.0","goal4range":"174-192","goal4adjective":"HiAvg","goal5name":"","goal5ritscore":"","goal5stderr":"","goal5range":"","goal5adjective":"","goal6name":"","goal6ritscore":"","goal6stderr":"","goal6range":"","goal6adjective":"","goal7name":"","goal7ritscore":"","goal7stderr":"","goal7range":"","goal7adjective":"","goal8name":"","goal8ritscore":"","goal8stderr":"","goal8range":"","goal8adjective":"","typicalfalltofallgrowth":"14","typicalfalltowintergrowth":"10","typicalfalltospringgrowth":"16","typicalwintertowintergrowth":"","typicalwintertospringgrowth":"","typicalspringtospringgrowth":"","projectedproficiencystudy1":"","projectedproficiencylevel1":"","projectedproficiencystudy2":"","projectedproficiencylevel2":"","projectedproficiencystudy3":"STAAR","projectedproficiencylevel3":"Approaches","projectedproficiencystudy4":"","projectedproficiencylevel4":"","projectedproficiencystudy5":"","projectedproficiencylevel5":"","projectedproficiencystudy6":"","projectedproficiencylevel6":"","projectedproficiencystudy7":"","projectedproficiencylevel7":"","projectedproficiencystudy8":"","projectedproficiencylevel8":"","projectedproficiencystudy9":"","projectedproficiencylevel9":"","projectedproficiencystudy10":"","projectedproficiencylevel10":"","classname":"1","teachername":"Beckley, Kristen","teacherid":"AssessAlpha","teacher_stateid":"","studentlastname":"D'Anieri","studentfirstname":"Adriana","studentmi":"","studentdateofbirth":"2018-05-29","studentethnicgroup":"Not Specified or Other","nweastandard_ethnicgroup":"Not Specified or Other","studentgender":"X","grade":"2","nweastandard_grade":"2","learningrate":"","termprojectedgrowth":"","termobservedgrowth":"","teststartdatelatestinterm":"","minstandarderror":""},{"termname":"Fall 2025-2026","districtname":"Alpha","district_stateid":"","schoolname":"Alpha West Palm Beach","school_stateid":"","studentid":"022-1250","student_stateid":"","subject":"Reading","course":"Reading","growthmeasureyn":"","normsreferencedata":"2025","wiselectedayfall":"1","wiselectedaywinter":"","wiselectedayspring":"","wipreviousayfall":"","wipreviousaywinter":"","wipreviousayspring":"","testtype":"Survey With Goals","testname":"Growth: Reading 2-5 CCSS 2010 1.1","testid":"","teststartdate":"2025-08-19","teststarttime":"8:52:48","testdurationminutes":"105","testritscore":"199","teststandarderror":"3.35","testpercentile":"80","achievementquintile":"HiAvg","percentcorrect":"60","rapidguessingpercentage":"0.0","falltofallprojectedgrowth":"","falltofallobservedgrowth":"","falltofallobservedgrowthse":"","falltofallmetprojectedgrowth":"","falltofallconditionalgrowthindex":"","falltofallconditionalgrowthpercentile":"","falltofallgrowthquintile":"","falltowinterprojectedgrowth":"","falltowinterobservedgrowth":"","falltowinterobservedgrowthse":"","falltowintermetprojectedgrowth":"","falltowinterconditionalgrowthindex":"","falltowinterconditionalgrowthpercentile":"","falltowintergrowthquintile":"","falltospringprojectedgrowth":"","falltospringobservedgrowth":"","falltospringobservedgrowthse":"","falltospringmetprojectedgrowth":"","falltospringconditionalgrowthindex":"","falltospringconditionalgrowthpercentile":"","falltospringgrowthquintile":"","wintertowinterprojectedgrowth":"","wintertowinterobservedgrowth":"","wintertowinterobservedgrowthse":"","wintertowintermetprojectedgrowth":"","wintertowinterconditionalgrowthindex":"","wintertowinterconditionalgrowthpercentile":"","wintertowintergrowthquintile":"","wintertospringprojectedgrowth":"","wintertospringobservedgrowth":"","wintertospringobservedgrowthse":"","wintertospringmetprojectedgrowth":"","wintertospringconditionalgrowthindex":"","wintertospringconditionalgrowthpercentile":"","wintertospringgrowthquintile":"","springtospringprojectedgrowth":"","springtospringobservedgrowth":"","springtospringobservedgrowthse":"","springtospringmetprojectedgrowth":"","springtospringconditionalgrowthindex":"","springtospringconditionalgrowthpercentile":"","springtospringgrowthquintile":"","lexilescore":"670L","lexilemin":"570L","lexilemax":"720L","quantilescore":"","quantilemin":"","quantilemax":"","goal1name":"Literary Text","goal1ritscore":"197.0","goal1stderr":"5.5","goal1range":"192-203","goal1adjective":"HiAvg","goal2name":"Informational Text","goal2ritscore":"201.0","goal2stderr":"5.7","goal2range":"195-207","goal2adjective":"High","goal3name":"Vocabulary","goal3ritscore":"199.0","goal3stderr":"6.5","goal3range":"193-205","goal3adjective":"HiAvg","goal4name":"","goal4ritscore":"","goal4stderr":"","goal4range":"","goal4adjective":"","goal5name":"","goal5ritscore":"","goal5stderr":"","goal5range":"","goal5adjective":"","goal6name":"","goal6ritscore":"","goal6stderr":"","goal6range":"","goal6adjective":"","goal7name":"","goal7ritscore":"","goal7stderr":"","goal7range":"","goal7adjective":"","goal8name":"","goal8ritscore":"","goal8stderr":"","goal8range":"","goal8adjective":"","typicalfalltofallgrowth":"9","typicalfalltowintergrowth":"4","typicalfalltospringgrowth":"8","typicalwintertowintergrowth":"","typicalwintertospringgrowth":"","typicalspringtospringgrowth":"","projectedproficiencystudy1":"","projectedproficiencylevel1":"","projectedproficiencystudy2":"","projectedproficiencylevel2":"","projectedproficiencystudy3":"STAAR","projectedproficiencylevel3":"Meets","projectedproficiencystudy4":"","projectedproficiencylevel4":"","projectedproficiencystudy5":"","projectedproficiencylevel5":"","projectedproficiencystudy6":"","projectedproficiencylevel6":"","projectedproficiencystudy7":"","projectedproficiencylevel7":"","projectedproficiencystudy8":"","projectedproficiencylevel8":"","projectedproficiencystudy9":"","projectedproficiencylevel9":"","projectedproficiencystudy10":"","projectedproficiencylevel10":"","classname":"1","teachername":"Beckley, Kristen","teacherid":"AssessAlpha","teacher_stateid":"","studentlastname":"Grunow","studentfirstname":"Hope","studentmi":"","studentdateofbirth":"2017-01-24","studentethnicgroup":"Not Specified or Other","nweastandard_ethnicgroup":"Not Specified or Other","studentgender":"F","grade":"3","nweastandard_grade":"3","learningrate":"","termprojectedgrowth":"","termobservedgrowth":"","teststartdatelatestinterm":"","minstandarderror":""},{"termname":"Fall 2025-2026","districtname":"Alpha","district_stateid":"","schoolname":"Alpha West Palm Beach","school_stateid":"","studentid":"022-1251","student_stateid":"","subject":"Reading","course":"Reading","growthmeasureyn":"","normsreferencedata":"2025","wiselectedayfall":"1","wiselectedaywinter":"","wiselectedayspring":"","wipreviousayfall":"","wipreviousaywinter":"","wipreviousayspring":"","testtype":"Survey With Goals","testname":"Growth: Reading 2-5 CCSS 2010 1.1","testid":"","teststartdate":"2025-08-19","teststarttime":"8:47:12","testdurationminutes":"96","testritscore":"204","teststandarderror":"3.26","testpercentile":"69","achievementquintile":"HiAvg","percentcorrect":"55","rapidguessingpercentage":"0.0","falltofallprojectedgrowth":"","falltofallobservedgrowth":"","falltofallobservedgrowthse":"","falltofallmetprojectedgrowth":"","falltofallconditionalgrowthindex":"","falltofallconditionalgrowthpercentile":"","falltofallgrowthquintile":"","falltowinterprojectedgrowth":"","falltowinterobservedgrowth":"","falltowinterobservedgrowthse":"","falltowintermetprojectedgrowth":"","falltowinterconditionalgrowthindex":"","falltowinterconditionalgrowthpercentile":"","falltowintergrowthquintile":"","falltospringprojectedgrowth":"","falltospringobservedgrowth":"","falltospringobservedgrowthse":"","falltospringmetprojectedgrowth":"","falltospringconditionalgrowthindex":"","falltospringconditionalgrowthpercentile":"","falltospringgrowthquintile":"","wintertowinterprojectedgrowth":"","wintertowinterobservedgrowth":"","wintertowinterobservedgrowthse":"","wintertowintermetprojectedgrowth":"","wintertowinterconditionalgrowthindex":"","wintertowinterconditionalgrowthpercentile":"","wintertowintergrowthquintile":"","wintertospringprojectedgrowth":"","wintertospringobservedgrowth":"","wintertospringobservedgrowthse":"","wintertospringmetprojectedgrowth":"","wintertospringconditionalgrowthindex":"","wintertospringconditionalgrowthpercentile":"","wintertospringgrowthquintile":"","springtospringprojectedgrowth":"","springtospringobservedgrowth":"","springtospringobservedgrowthse":"","springtospringmetprojectedgrowth":"","springtospringconditionalgrowthindex":"","springtospringconditionalgrowthpercentile":"","springtospringgrowthquintile":"","lexilescore":"765L","lexilemin":"665L","lexilemax":"815L","quantilescore":"","quantilemin":"","quantilemax":"","goal1name":"Literary Text","goal1ritscore":"205.0","goal1stderr":"5.4","goal1range":"200-210","goal1adjective":"HiAvg","goal2name":"Informational Text","goal2ritscore":"205.0","goal2stderr":"5.6","goal2range":"199-211","goal2adjective":"HiAvg","goal3name":"Vocabulary","goal3ritscore":"200.0","goal3stderr":"6.1","goal3range":"194-206","goal3adjective":"Avg","goal4name":"","goal4ritscore":"","goal4stderr":"","goal4range":"","goal4adjective":"","goal5name":"","goal5ritscore":"","goal5stderr":"","goal5range":"","goal5adjective":"","goal6name":"","goal6ritscore":"","goal6stderr":"","goal6range":"","goal6adjective":"","goal7name":"","goal7ritscore":"","goal7stderr":"","goal7range":"","goal7adjective":"","goal8name":"","goal8ritscore":"","goal8stderr":"","goal8range":"","goal8adjective":"","typicalfalltofallgrowth":"7","typicalfalltowintergrowth":"3","typicalfalltospringgrowth":"6","typicalwintertowintergrowth":"","typicalwintertospringgrowth":"","typicalspringtospringgrowth":"","projectedproficiencystudy1":"","projectedproficiencylevel1":"","projectedproficiencystudy2":"","projectedproficiencylevel2":"","projectedproficiencystudy3":"STAAR","projectedproficiencylevel3":"Meets","projectedproficiencystudy4":"","projectedproficiencylevel4":"","projectedproficiencystudy5":"","projectedproficiencylevel5":"","projectedproficiencystudy6":"","projectedproficiencylevel6":"","projectedproficiencystudy7":"","projectedproficiencylevel7":"","projectedproficiencystudy8":"","projectedproficiencylevel8":"","projectedproficiencystudy9":"","projectedproficiencylevel9":"","projectedproficiencystudy10":"","projectedproficiencylevel10":"","classname":"2","teachername":"Beckley, Kristen","teacherid":"AssessAlpha","teacher_stateid":"","studentlastname":"Grunow","studentfirstname":"Johnny","studentmi":"","studentdateofbirth":"2015-12-01","studentethnicgroup":"Not Specified or Other","nweastandard_ethnicgroup":"Not Specified or Other","studentgender":"M","grade":"4","nweastandard_grade":"4","learningrate":"","termprojectedgrowth":"","termobservedgrowth":"","teststartdatelatestinterm":"","minstandarderror":""},{"termname":"Fall 2025-2026","districtname":"Alpha","district_stateid":"","schoolname":"Alpha West Palm Beach","school_stateid":"","studentid":"022-1840","student_stateid":"","subject":"Reading","course":"Reading","growthmeasureyn":"","normsreferencedata":"2025","wiselectedayfall":"1","wiselectedaywinter":"","wiselectedayspring":"","wipreviousayfall":"","wipreviousaywinter":"","wipreviousayspring":"","testtype":"Survey With Goals","testname":"Growth: Reading K-2 CCSS 2010 1.1","testid":"","teststartdate":"2025-08-19","teststarttime":"8:49:24","testdurationminutes":"25","testritscore":"142","teststandarderror":"3.25","testpercentile":"72","achievementquintile":"HiAvg","percentcorrect":"58","rapidguessingpercentage":"0.0","falltofallprojectedgrowth":"","falltofallobservedgrowth":"","falltofallobservedgrowthse":"","falltofallmetprojectedgrowth":"","falltofallconditionalgrowthindex":"","falltofallconditionalgrowthpercentile":"","falltofallgrowthquintile":"","falltowinterprojectedgrowth":"","falltowinterobservedgrowth":"","falltowinterobservedgrowthse":"","falltowintermetprojectedgrowth":"","falltowinterconditionalgrowthindex":"","falltowinterconditionalgrowthpercentile":"","falltowintergrowthquintile":"","falltospringprojectedgrowth":"","falltospringobservedgrowth":"","falltospringobservedgrowthse":"","falltospringmetprojectedgrowth":"","falltospringconditionalgrowthindex":"","falltospringconditionalgrowthpercentile":"","falltospringgrowthquintile":"","wintertowinterprojectedgrowth":"","wintertowinterobservedgrowth":"","wintertowinterobservedgrowthse":"","wintertowintermetprojectedgrowth":"","wintertowinterconditionalgrowthindex":"","wintertowinterconditionalgrowthpercentile":"","wintertowintergrowthquintile":"","wintertospringprojectedgrowth":"","wintertospringobservedgrowth":"","wintertospringobservedgrowthse":"","wintertospringmetprojectedgrowth":"","wintertospringconditionalgrowthindex":"","wintertospringconditionalgrowthpercentile":"","wintertospringgrowthquintile":"","springtospringprojectedgrowth":"","springtospringobservedgrowth":"","springtospringobservedgrowthse":"","springtospringmetprojectedgrowth":"","springtospringconditionalgrowthindex":"","springtospringconditionalgrowthpercentile":"","springtospringgrowthquintile":"","lexilescore":"BR400L","lexilemin":"BR400L","lexilemax":"BR380L","quantilescore":"","quantilemin":"","quantilemax":"","goal1name":"Foundational Skills","goal1ritscore":"126.0","goal1stderr":"7.0","goal1range":"119-133","goal1adjective":"Low","goal2name":"Language and Writing","goal2ritscore":"137.0","goal2stderr":"6.2","goal2range":"131-143","goal2adjective":"Avg","goal3name":"Literature and Informational Text","goal3ritscore":"159.0","goal3stderr":"8.1","goal3range":"151-167","goal3adjective":"High","goal4name":"Vocabulary Use and Functions","goal4ritscore":"149","goal4stderr":"7.1","goal4range":"142-156","goal4adjective":"High","goal5name":"","goal5ritscore":"","goal5stderr":"","goal5range":"","goal5adjective":"","goal6name":"","goal6ritscore":"","goal6stderr":"","goal6range":"","goal6adjective":"","goal7name":"","goal7ritscore":"","goal7stderr":"","goal7range":"","goal7adjective":"","goal8name":"","goal8ritscore":"","goal8stderr":"","goal8range":"","goal8adjective":"","typicalfalltofallgrowth":"19","typicalfalltowintergrowth":"8","typicalfalltospringgrowth":"14","typicalwintertowintergrowth":"","typicalwintertospringgrowth":"","typicalspringtospringgrowth":"","projectedproficiencystudy1":"","projectedproficiencylevel1":"","projectedproficiencystudy2":"","projectedproficiencylevel2":"","projectedproficiencystudy3":"","projectedproficiencylevel3":"","projectedproficiencystudy4":"","projectedproficiencylevel4":"","projectedproficiencystudy5":"","projectedproficiencylevel5":"","projectedproficiencystudy6":"","projectedproficiencylevel6":"","projectedproficiencystudy7":"","projectedproficiencylevel7":"","projectedproficiencystudy8":"","projectedproficiencylevel8":"","projectedproficiencystudy9":"","projectedproficiencylevel9":"","projectedproficiencystudy10":"","projectedproficiencylevel10":"","classname":"0","teachername":"Beckley, Kristen","teacherid":"AssessAlpha","teacher_stateid":"","studentlastname":"Grunow","studentfirstname":"Elizabeth","studentmi":"","studentdateofbirth":"2020-06-02","studentethnicgroup":"Not Specified or Other","nweastandard_ethnicgroup":"Not Specified or Other","studentgender":"F","grade":"K","nweastandard_grade":"K","learningrate":"","termprojectedgrowth":"","termobservedgrowth":"","teststartdatelatestinterm":"","minstandarderror":""},{"termname":"Fall 2025-2026","districtname":"Alpha","district_stateid":"","schoolname":"Alpha West Palm Beach","school_stateid":"","studentid":"022-1899","student_stateid":"","subject":"Reading","course":"Reading","growthmeasureyn":"","normsreferencedata":"2025","wiselectedayfall":"1","wiselectedaywinter":"","wiselectedayspring":"","wipreviousayfall":"","wipreviousaywinter":"","wipreviousayspring":"","testtype":"Survey With Goals","testname":"Growth: Reading 2-5 CCSS 2010 1.1","testid":"","teststartdate":"2025-08-19","teststarttime":"8:50:17","testdurationminutes":"24","testritscore":"169","teststandarderror":"3.38","testpercentile":"50","achievementquintile":"Avg","percentcorrect":"45","rapidguessingpercentage":"5.0","falltofallprojectedgrowth":"","falltofallobservedgrowth":"","falltofallobservedgrowthse":"","falltofallmetprojectedgrowth":"","falltofallconditionalgrowthindex":"","falltofallconditionalgrowthpercentile":"","falltofallgrowthquintile":"","falltowinterprojectedgrowth":"","falltowinterobservedgrowth":"","falltowinterobservedgrowthse":"","falltowintermetprojectedgrowth":"","falltowinterconditionalgrowthindex":"","falltowinterconditionalgrowthpercentile":"","falltowintergrowthquintile":"","falltospringprojectedgrowth":"","falltospringobservedgrowth":"","falltospringobservedgrowthse":"","falltospringmetprojectedgrowth":"","falltospringconditionalgrowthindex":"","falltospringconditionalgrowthpercentile":"","falltospringgrowthquintile":"","wintertowinterprojectedgrowth":"","wintertowinterobservedgrowth":"","wintertowinterobservedgrowthse":"","wintertowintermetprojectedgrowth":"","wintertowinterconditionalgrowthindex":"","wintertowinterconditionalgrowthpercentile":"","wintertowintergrowthquintile":"","wintertospringprojectedgrowth":"","wintertospringobservedgrowth":"","wintertospringobservedgrowthse":"","wintertospringmetprojectedgrowth":"","wintertospringconditionalgrowthindex":"","wintertospringconditionalgrowthpercentile":"","wintertospringgrowthquintile":"","springtospringprojectedgrowth":"","springtospringobservedgrowth":"","springtospringobservedgrowthse":"","springtospringmetprojectedgrowth":"","springtospringconditionalgrowthindex":"","springtospringconditionalgrowthpercentile":"","springtospringgrowthquintile":"","lexilescore":"90L","lexilemin":"BR10L","lexilemax":"140L","quantilescore":"","quantilemin":"","quantilemax":"","goal1name":"Literary Text","goal1ritscore":"172.0","goal1stderr":"5.9","goal1range":"166-178","goal1adjective":"Avg","goal2name":"Informational Text","goal2ritscore":"170.0","goal2stderr":"5.3","goal2range":"165-175","goal2adjective":"Avg","goal3name":"Vocabulary","goal3ritscore":"164.0","goal3stderr":"6.8","goal3range":"157-171","goal3adjective":"LoAvg","goal4name":"","goal4ritscore":"","goal4stderr":"","goal4range":"","goal4adjective":"","goal5name":"","goal5ritscore":"","goal5stderr":"","goal5range":"","goal5adjective":"","goal6name":"","goal6ritscore":"","goal6stderr":"","goal6range":"","goal6adjective":"","goal7name":"","goal7ritscore":"","goal7stderr":"","goal7range":"","goal7adjective":"","goal8name":"","goal8ritscore":"","goal8stderr":"","goal8range":"","goal8adjective":"","typicalfalltofallgrowth":"16","typicalfalltowintergrowth":"8","typicalfalltospringgrowth":"13","typicalwintertowintergrowth":"","typicalwintertospringgrowth":"","typicalspringtospringgrowth":"","projectedproficiencystudy1":"","projectedproficiencylevel1":"","projectedproficiencystudy2":"","projectedproficiencylevel2":"","projectedproficiencystudy3":"STAAR","projectedproficiencylevel3":"Approaches","projectedproficiencystudy4":"","projectedproficiencylevel4":"","projectedproficiencystudy5":"","projectedproficiencylevel5":"","projectedproficiencystudy6":"","projectedproficiencylevel6":"","projectedproficiencystudy7":"","projectedproficiencylevel7":"","projectedproficiencystudy8":"","projectedproficiencylevel8":"","projectedproficiencystudy9":"","projectedproficiencylevel9":"","projectedproficiencystudy10":"","projectedproficiencylevel10":"","classname":"1","teachername":"Beckley, Kristen","teacherid":"AssessAlpha","teacher_stateid":"","studentlastname":"D'Anieri","studentfirstname":"Adriana","studentmi":"","studentdateofbirth":"2018-05-29","studentethnicgroup":"Not Specified or Other","nweastandard_ethnicgroup":"Not Specified or Other","studentgender":"X","grade":"2","nweastandard_grade":"2","learningrate":"","termprojectedgrowth":"","termobservedgrowth":"","teststartdatelatestinterm":"","minstandarderror":""}]